pds4indextools/_version.py
pds4indextools/default_config.yaml
pds4indextools/index_label_template_pds.xml
pds4indextools/pds4_create_collection_product.py
pds4indextools/pds4_create_xml_index.py
rms_pds4indextools-1.4.0.dist-info/licenses/LICENSE
rms_pds4indextools-1.4.0.dist-info/METADATA
rms_pds4indextools-1.4.0.dist-info/WHEEL
rms_pds4indextools-1.4.0.dist-info/entry_points.txt
rms_pds4indextools-1.4.0.dist-info/top_level.txt
rms_pds4indextools-1.4.0.dist-info/RECORD
