Metadata-Version: 2.4
Name: rms-pds4indextools
Version: 1.4.0
Summary: pds4indextools
Maintainer-email: "Emilie R. Simpson" <esimpson@seti.org>
License: Apache-2.0
Project-URL: Homepage, https://github.com/SETI/rms-pds4indextools
Project-URL: Documentation, https://rms-pds4indextools.readthedocs.io/en/latest
Project-URL: Repository, https://github.com/SETI/rms-pds4indextools
Project-URL: Source, https://github.com/SETI/rms-pds4indextools
Project-URL: Issues, https://github.com/SETI/rms-pds4indextools/issues
Keywords: pds4indextools
Classifier: Development Status :: 5 - Production/Stable
Classifier: Natural Language :: English
Classifier: Topic :: Scientific/Engineering
Classifier: Topic :: Scientific/Engineering :: Astronomy
Classifier: Topic :: Software Development :: Libraries :: Python Modules
Classifier: Topic :: Utilities
Classifier: License :: OSI Approved :: Apache Software License
Classifier: Programming Language :: Python :: 3.9
Classifier: Programming Language :: Python :: 3.10
Classifier: Programming Language :: Python :: 3.11
Classifier: Programming Language :: Python :: 3.12
Classifier: Programming Language :: Python :: 3.13
Classifier: Operating System :: MacOS :: MacOS X
Classifier: Operating System :: POSIX :: Linux
Classifier: Operating System :: Microsoft :: Windows
Requires-Python: >=3.9
License-File: LICENSE
Requires-Dist: lxml
Requires-Dist: pandas
Requires-Dist: pyyaml
Requires-Dist: requests
Requires-Dist: rms-pdstemplate
Dynamic: license-file
